online_store_by_podpivas/__init__.py
online_store_by_podpivas/__main__.py
online_store_by_podpivas/order_management.py
online_store_by_podpivas/user_management.py
online_store_by_podpivas-0.1.1.dist-info/METADATA
online_store_by_podpivas-0.1.1.dist-info/WHEEL
online_store_by_podpivas-0.1.1.dist-info/top_level.txt
online_store_by_podpivas-0.1.1.dist-info/RECORD
