Metadata-Version: 2.1
Name: online-store-by-podpivas
Version: 0.1.1
Summary: Исполняемый пакет для управления пользователями и заказами в онлайн-магазине
Author-email: podpivas <k.shaykhraziev@edu.centraluniversity.ru>
License: MIT
Requires-Python: >=3.8
Requires-Dist: requests>=2.25.1
Requires-Dist: numpy>=1.19.2
